genomicassertions/__init__.py
genomicassertions/readassertions.py
genomicassertions/variantassertions.py
genomicassertions-0.2.3.dist-info/DESCRIPTION.rst
genomicassertions-0.2.3.dist-info/METADATA
genomicassertions-0.2.3.dist-info/RECORD
genomicassertions-0.2.3.dist-info/WHEEL
genomicassertions-0.2.3.dist-info/metadata.json
genomicassertions-0.2.3.dist-info/top_level.txt
