Metadata-Version: 2.0
Name: genomicassertions
Version: 0.2.3
Summary: A package to test common files in genomics (.vcf.gz, .bam)
Home-page: https://github.com/dakl/genomicassertions
Author: Daniel Klevebring
Author-email: daniel.klevebring@gmail.com
License: UNKNOWN
Download-URL: https://github.com/dakl/genomicassertions/tarball/v0.2.3
Keywords: testing,genomics
Platform: UNKNOWN
Requires-Dist: PyVCF
Requires-Dist: pysam
